python_heap/__init__.py
python_heap/heap.py
python_heap/test_heap.py
python_heap-0.1.0.dist-info/licenses/LICENSE
python_heap-0.1.0.dist-info/METADATA
python_heap-0.1.0.dist-info/WHEEL
python_heap-0.1.0.dist-info/top_level.txt
python_heap-0.1.0.dist-info/RECORD
