Metadata-Version: 2.4
Name: python_heap
Version: 0.1.0
Summary: Heap implementation in python because heapq sucks!
Author-email: Saurabh <sourabhmahra91@gmail.com>
Requires-Python: >=3.10
License-File: LICENSE
Dynamic: license-file
